Workbook
Name page\x2dtotal: #REF!
Name page\x2dtotal\x2dmaster0: #REF!

Sheet Data_BI
A1: Название | B1: Тип | C1: 2уровень | D1: Ф/Ю | E1: Код валюты | F1: Расшифровка | G1: Сумма | H1: Месяц | I1: Комментарии | J1: УК | K1: Группа
A2: 1) ЧПД | B2: Процентный доход | C2: Проценты по депозиту в ЦБ | D2: Прочее | E2: RUB | F2: ‭Процентные доходы по депозитам в ЦБ РФ‬ | G2: 220656000 | H2: 45658 | J2: Учетные данные | K2: Доход | L2: =(ISNUMBER(G2))-1 -> 0
A3: 2) Комиссии - нетто | B3: Комиссионный расход | C3: Комиссия за переводы | D3: Прочее | E3: RUB | F3: Комиссии в ФФ КЗ | G3: 1.7684847e+08 | H3: 45658 | J3: Управл.Корр | K3: Расход | L3: =(ISNUMBER(G3))-1 -> 0
A4: 3) FX | B4: Безнал | C4: Доход безнал | D4: Прочее | E4: USD | G4: 1.4812088e+08 | H4: 45658 | J4: Учетные данные | K4: Доход | L4: =(ISNUMBER(G4))-1 -> 0
A5: 2) Комиссии - нетто | B5: Комиссионный доход | C5: РКО ФЛ | D5: ФЛ | E5: RUB | F5: ‭Комиссия за расчетное обслуживание ФИЗ. ЛИЦ в рублях‬ | G5: 1.2371387e+08 | H5: 45658 | J5: Учетные данные | K5: Доход | L5: =(ISNUMBER(G5))-1 -> 0
A6: 7) Нетто эффект резервов на ОПУ | B6: Восстановление резервов | C6: =Data_BI!#REF! -> #REF! | D6: Прочее | E6: RUB | F6: ‭РВП по 611-П Восстановление резерва Денежные ср-ва в пути. (47425)‬ | G6: 98348830 | H6: 45658 | J6: Учетные данные | K6: Резервы | L6: =(ISNUMBER(G6))-1 -> 0
A7: 3) FX | B7: Безнал | C7: Доход безнал | D7: Прочее | E7: EUR | G7: 90179795 | H7: 45658 | J7: Учетные данные | K7: Доход | L7: =(ISNUMBER(G7))-1 -> 0
A8: 7) Нетто эффект резервов на ОПУ | B8: Восстановление резервов | C8: =Data_BI!#REF! -> #REF! | D8: Прочее | E8: RUB | F8: ‭РВПС 590-п Доходы от восст.резервов по МБК‬ | G8: 66000000 | H8: 45658 | J8: Учетные данные | K8: Резервы | L8: =(ISNUMBER(G8))-1 -> 0
A9: 3) FX | B9: Безнал | C9: Доход безнал | D9: Прочее | E9: CNY | G9: 51323664 | H9: 45658 | J9: Учетные данные | K9: Доход | L9: =(ISNUMBER(G9))-1 -> 0
A10: 3) FX | B10: Безнал | C10: Доход безнал | D10: Прочее | E10: KZT | G10: 47140831 | H10: 45658 | J10: Учетные данные | K10: Доход | L10: =(ISNUMBER(G10))-1 -> 0
A11: 7) Нетто эффект резервов на ОПУ | B11: Восстановление резервов | C11: =Data_BI!#REF! -> #REF! | D11: Прочее | E11: RUB | F11: ‭Доходы, увеличивающие операционные доходы, на разницу между резервами на возможные потери и оценочными резервами под ожидаемые кредитные убытки‬ | G11: 38300542 | H11: 45658 | J11: Учетные данные | K11: Резервы | L11: =(ISNUMBER(G11))-1 -> 0
A12: 2) Комиссии - нетто | B12: Комиссионный доход | C12: По брокерским счетам | D12: Прочее | E12: RUB | F12: ‭Комиссия по специальным брок. счетам и по операциям клиентов в руб. без НДС (CLIENT)‬ | G12: 37445578 | H12: 45658 | J12: Учетные данные | K12: Доход | L12: =(ISNUMBER(G12))-1 -> 0
A13: 1) ЧПД | B13: Процентный доход | C13: Проценты по ЦБ в портфеле | D13: Прочее | E13: RUB | F13: ‭НКД по облигациям прочих резидентов по АС в рублях‬ | G13: 36920497 | H13: 45658 | J13: Учетные данные | K13: Доход | L13: =(ISNUMBER(G13))-1 -> 0
A14: 1) ЧПД | B14: Процентный доход | C14: Проценты по РЕПО | D14: Прочее | E14: RUB | F14: ‭Доходы от сделок РЕПО в руб.‬ | G14: 36171583 | H14: 45658 | J14: Учетные данные | K14: Доход | L14: =(ISNUMBER(G14))-1 -> 0
A15: 4) ЧТД | B15: Переоценка ЧТД | C15: Доходы от переоценки ЦБ | D15: Прочее | E15: RUB | F15: ‭Положительная переоценка долевых ценных бумаг по ССчП/У прочих резидентов ‬ | G15: 31000000 | H15: 45658 | J15: Учетные данные | K15: Доход | L15: =(ISNUMBER(G15))-1 -> 0
A16: 3) FX | B16: Наличные | C16: Доход налич | D16: Прочее | E16: EUR | G16: 29179361 | H16: 45658 | J16: Учетные данные | K16: Доход | L16: =(ISNUMBER(G16))-1 -> 0
A17: 3) FX | B17: Безнал | C17: Доход безнал | D17: Прочее | E17: USD | G17: 23865668 | H17: 45658 | J17: Учетные данные | K17: Доход | L17: =(ISNUMBER(G17))-1 -> 0
A18: 2) Комиссии - нетто | B18: Комиссионный доход | C18: РКО ЮЛ | D18: ЮЛ | E18: RUB | F18: ‭Комиссия за перевод средств ЮР.ЛИЦ, в руб. без НДС‬ | G18: 20365258 | H18: 45658 | J18: Учетные данные | K18: Доход | L18: =(ISNUMBER(G18))-1 -> 0
A19: 1) ЧПД | B19: Процентный доход | C19: Проценты по ЦБ в портфеле | D19: Прочее | E19: RUB | F19: ‭НКД по облигациям КО по АС в рублях‬ | G19: 17081880 | H19: 45658 | J19: Учетные данные | K19: Доход | L19: =(ISNUMBER(G19))-1 -> 0
A20: 3) FX | B20: Наличные | C20: Доход налич | D20: Прочее | E20: USD | G20: 16957229 | H20: 45658 | J20: Учетные данные | K20: Доход | L20: =(ISNUMBER(G20))-1 -> 0
A21: 1) ЧПД | B21: Процентный доход | C21: Проценты по кредитам ЮЛ/МБК | D21: Прочее | E21: RUB | F21: ‭Процентные доходы по межбанковским кредитам в рублях‬ | G21: 16885068 | H21: 45658 | J21: Учетные данные | K21: Доход | L21: =(ISNUMBER(G21))-1 -> 0
A22: 7) Нетто эффект резервов на ОПУ | B22: Восстановление резервов | C22: =Data_BI!#REF! -> #REF! | D22: Прочее | E22: RUB | F22: ‭РВП по 611-П по остаткам на корсчетах ‬ | G22: 16056714 | H22: 45658 | I22: Согласно ст 292 НК РФ бан имеет право признавать только Резерв поод ссудную задолженность по 590-П | J22: Учетные данные | K22: Резервы | L22: =(ISNUMBER(G22))-1 -> 0
A23: 1) ЧПД | B23: Процентный доход | C23: Проценты по кредитам ЮЛ/МБК | D23: ЮЛ | E23: RUB | F23: ‭Проценты по кредитам предоставл. юр.лицам‬ | G23: 14925084 | H23: 45658 | J23: Учетные данные | K23: Доход | L23: =(ISNUMBER(G23))-1 -> 0
A24: 3) FX | B24: Безнал | C24: Доход безнал | D24: Прочее | E24: KZT | G24: 13740364 | H24: 45658 | J24: Учетные данные | K24: Доход | L24: =(ISNUMBER(G24))-1 -> 0
A25: 2) Комиссии - нетто | B25: Комиссионный доход | C25: РКО ЮЛ | D25: ЮЛ | E25: RUB | F25: ‭Комиссия за доп. услуги ЮР. ЛИЦ (без НДС) в руб.‬ | G25: 13370604 | H25: 45658 | J25: Учетные данные | K25: Доход | L25: =(ISNUMBER(G25))-1 -> 0
A26: 7) Нетто эффект резервов на ОПУ | B26: Восстановление резервов | C26: =Data_BI!$B10 -> Безнал | D26: Прочее | E26: RUB | F26: ‭РВП по 611-П по внутрихозяйственным операциям (счет 60324)‬ | G26: 13264965 | H26: 45658 | I26: Согласно ст 292 НК РФ бан имеет право признавать только Резерв поод ссудную задолженность по 590-П | J26: Учетные данные | K26: Резервы | L26: =(ISNUMBER(G26))-1 -> 0
A27: 3) FX | B27: Безнал | C27: Доход безнал | D27: Прочее | E27: AED | G27: 12068886 | H27: 45658 | J27: Учетные данные | K27: Доход | L27: =(ISNUMBER(G27))-1 -> 0
A28: 3) FX | B28: Безнал | C28: Доход безнал | D28: Прочее | E28: USD | G28: 10073948 | H28: 45658 | J28: Учетные данные | K28: Доход | L28: =(ISNUMBER(G28))-1 -> 0
A29: 2) Комиссии - нетто | B29: Комиссионный доход | C29: РКО ФЛ | D29: ФЛ | E29: RUB | F29: ‭Комиссия за расчетное обслуживание ФИЗ. ЛИЦ в ин.валюте‬ | G29: 9561615.6 | H29: 45658 | J29: Учетные данные | K29: Доход | L29: =(ISNUMBER(G29))-1 -> 0
A30: 1) ЧПД | B30: Процентный доход | C30: Проценты по кредитам ФЛ | D30: ФЛ | E30: RUB | F30: ‭Проценты по кредитм физлиц (срочные)- внутренний‬ | G30: 9451298.9 | H30: 45658 | J30: Учетные данные | K30: Доход | L30: =(ISNUMBER(G30))-1 -> 0
A31: 2) Комиссии - нетто | B31: Комиссионный доход | C31: РКО ЮЛ | D31: ЮЛ | E31: RUB | F31: ‭Комиссия за перевод средств ЮР.ЛИЦ, инв. вал‬ | G31: 8963055.7 | H31: 45658 | J31: Учетные данные | K31: Доход | L31: =(ISNUMBER(G31))-1 -> 0
A32: 7) Нетто эффект резервов на ОПУ | B32: Восстановление резервов | C32: =Data_BI!#REF! -> #REF! | D32: Прочее | E32: RUB | F32: ‭РВП по 611-П по другим активам и прочим операциям (47425)‬ | G32: 8740484.3 | H32: 45658 | I32: Согласно ст 292 НК РФ бан имеет право признавать только Резерв поод ссудную задолженность по 590-П | J32: Учетные данные | K32: Резервы | L32: =(ISNUMBER(G32))-1 -> 0
A33: 3) FX | B33: Безнал | C33: Доход безнал | D33: Прочее | E33: AED | G33: 7527124.1 | H33: 45658 | J33: Учетные данные | K33: Доход | L33: =(ISNUMBER(G33))-1 -> 0
A34: 2) Комиссии - нетто | B34: Комиссионный доход | C34: РКО ФЛ | D34: ФЛ | E34: RUB | F34: ‭Комиссия за перевод средств со счетов ФИЗ.ЛИЦ в ин.валюте‬ | G34: 7286208.5 | H34: 45658 | J34: Учетные данные | K34: Доход | L34: =(ISNUMBER(G34))-1 -> 0
A35: 2) Комиссии - нетто | B35: Комиссионный доход | C35: РКО ЮЛ | D35: ЮЛ | E35: RUB | F35: ‭Комиссия за валютный контроль ЮР.ЛИЦ в рублях облаг.НДС‬ | G35: 7227344.6 | H35: 45658 | J35: Учетные данные | K35: Доход | L35: =(ISNUMBER(G35))-1 -> 0
A36: 7) Нетто эффект резервов на ОПУ | B36: Восстановление резервов | C36: =Data_BI!#REF! -> #REF! | D36: Прочее | E36: RUB | F36: ‭Доходы от восстановления оценочных резервов по облигациям прочих резидентов‬ | G36: 6526218.4 | H36: 45658 | J36: Учетные данные | K36: Резервы | L36: =(ISNUMBER(G36))-1 -> 0
A37: 2) Комиссии - нетто | B37: Комиссионный доход | C37: РКО ЮЛ | D37: ЮЛ | E37: RUB | F37: ‭Комиссия за пакет обслуживания ЮР. ЛИЦ.‬ | G37: 5530150 | H37: 45658 | J37: Учетные данные | K37: Доход | L37: =(ISNUMBER(G37))-1 -> 0
A38: 7) Нетто эффект резервов на ОПУ | B38: Восстановление резервов | C38: =Data_BI!#REF! -> #REF! | D38: ЮЛ | E38: RUB | F38: ‭Доходы от создания оценочных резервов по кредитам юр. лиц резидентов‬ | G38: 5457123.9 | H38: 45658 | J38: Учетные данные | K38: Резервы | L38: =(ISNUMBER(G38))-1 -> 0
A39: 5) Доходы от участия в капитале | B39: Доходы от участия в капитале | D39: Прочее | E39: RUB | F39: ‭Дивиденды от вложений в акции организаций - резидентов‬ | G39: 5312300 | H39: 45658 | J39: Учетные данные | K39: Доход | L39: =(ISNUMBER(G39))-1 -> 0
A40: 1) ЧПД | B40: Процентный доход | C40: Проценты по кредитам ЮЛ/МБК | D40: Прочее | E40: RUB | F40: ‭Проценты по кредитам, предоставленным негосударственным финансовым организациям‬ | G40: 5246340.3 | H40: 45658 | J40: Учетные данные | K40: Доход | L40: =(ISNUMBER(G40))-1 -> 0
A41: 2) Комиссии - нетто | B41: Комиссионный доход | C41: РКО ФЛ | D41: Прочее | E41: RUB | F41: ‭Комиссия за взнос наличной ин.валюты через кассу Банка на счет клиента‬ | G41: 4957545 | H41: 45658 | J41: Учетные данные | K41: Доход | L41: =(ISNUMBER(G41))-1 -> 0
A42: 7) Нетто эффект резервов на ОПУ | B42: Восстановление резервов | C42: =Data_BI!#REF! -> #REF! | D42: Прочее | E42: RUB | F42: ‭РВП по 611-П по остаткам на корсчетах в банках-нерезидентах ‬ | G42: 4946432.4 | H42: 45658 | I42: Согласно ст 292 НК РФ бан имеет право признавать только Резерв поод ссудную задолженность по 590-П | J42: Учетные данные | K42: Резервы | L42: =(ISNUMBER(G42))-1 -> 0
A43: 1) ЧПД | B43: Процентный доход | C43: Проценты по ЦБ в портфеле | D43: Прочее | E43: RUB | F43: ‭НДД по ЦФА на денежные требования оцениваемые по АС в рублях‬ | G43: 4881244.2 | H43: 45658 | J43: Учетные данные | K43: Доход | L43: =(ISNUMBER(G43))-1 -> 0
A44: 3) FX | B44: Безнал | C44: Доход безнал | D44: Прочее | E44: TRY | G44: 4623720.7 | H44: 45658 | J44: Учетные данные | K44: Доход | L44: =(ISNUMBER(G44))-1 -> 0
A45: 2) Комиссии - нетто | B45: Комиссионный доход | C45: Платежные системы | D45: Прочее | E45: RUB | F45: ‭Расчеты с НПС МИР в руб‬ | G45: 4257789.2 | H45: 45658 | J45: Учетные данные | K45: Доход | L45: =(ISNUMBER(G45))-1 -> 0
A46: 7) Нетто эффект резервов на ОПУ | B46: Восстановление резервов | C46: =Data_BI!#REF! -> #REF! | D46: ФЛ | E46: RUB | F46: ‭РВПС 590-п Доходы от восст.резервов по кредит.физическим лицам‬ | G46: 4076384.1 | H46: 45658 | J46: Учетные данные | K46: Резервы | L46: =(ISNUMBER(G46))-1 -> 0
A47: 2) Комиссии - нетто | B47: Комиссионный доход | C47: Карта инвестора | D47: ФЛ | E47: RUB | F47: ‭Комиссия за информационно-технологическое взаимодействие с Турлов Фэмили Оффис Секьюритиз (ЗАО) ЛТД‬ | G47: 3885664.4 | H47: 45658 | J47: Учетные данные | K47: Доход | L47: =(ISNUMBER(G47))-1 -> 0
A48: 7) Нетто эффект резервов на ОПУ | B48: Восстановление резервов | C48: =Data_BI!#REF! -> #REF! | D48: ЮЛ | E48: RUB | F48: ‭РВП по 611-П Доходы от созданию РВП по кредитным линиям предоставленной юр.лицам‬ | G48: 3871582.8 | H48: 45658 | J48: Учетные данные | K48: Резервы | L48: =(ISNUMBER(G48))-1 -> 0
A49: 4) ЧТД | B49: Доходы от операций с ЦБ | C49: Доходы от операций с ЦБ | D49: Прочее | E49: RUB | F49: ‭Доход от операций по облигациям прочих резидентов по АС в рублях‬ | G49: 3592109.1 | H49: 45658 | J49: Учетные данные | K49: Доход | L49: =(ISNUMBER(G49))-1 -> 0
A50: 2) Комиссии - нетто | B50: Комиссионный доход | C50: Карта инвестора | D50: ФЛ | E50: RUB | F50: ‭Комиссия за информационно-технологическое взаимодействие с ООО "ФРИДОМ ФИНАНС АРМЕНИЯ"‬ | G50: 3462518.1 | H50: 45658 | J50: Учетные данные | K50: Доход | L50: =(ISNUMBER(G50))-1 -> 0
A51: 7) Нетто эффект резервов на ОПУ | B51: Восстановление резервов | C51: =Data_BI!#REF! -> #REF! | D51: Прочее | E51: RUB | F51: ‭РВП по 611-П Восстановление резерва по вложениям в долговые ЦБ прочих резидентов оцениваемых по амортизированной стоимости ‬ | G51: 3269723.7 | H51: 45658 | I51: Согласно ст 292 НК РФ бан имеет право признавать только Резерв поод ссудную задолженность по 590-П | J51: Учетные данные | K51: Резервы | L51: =(ISNUMBER(G51))-1 -> 0
A52: 3) FX | B52: Безнал | C52: Доход безнал | D52: Прочее | E52: USD | G52: 3176939.8 | H52: 45658 | J52: Учетные данные | K52: Доход | L52: =(ISNUMBER(G52))-1 -> 0
A53: 1) ЧПД | B53: Процентный доход | C53: Доход от пересчета начисленных процентов при досрочном закрытии депозита | D53: ФЛ | E53: RUB | F53: ‭Доходы от пересчета начисленных процентов при досрочном закрытии депозита - физ.лиц.-резид. в рублях‬ | G53: 3094958.4 | H53: 45658 | J53: Учетные данные | K53: Доход | L53: =(ISNUMBER(G53))-1 -> 0
A54: 3) FX | B54: Безнал | C54: Доход безнал | D54: Прочее | E54: EUR | G54: 2978636 | H54: 45658 | J54: Учетные данные | K54: Доход | L54: =(ISNUMBER(G54))-1 -> 0
A55: 1) ЧПД | B55: Процентный доход | C55: Проценты по ЦБ в портфеле | D55: Прочее | E55: RUB | F55: ‭НКД по облигациям прочих резидентов по ССчПСД в рублях‬ | G55: 2969466.8 | H55: 45658 | J55: Учетные данные | K55: Доход | L55: =(ISNUMBER(G55))-1 -> 0
A56: 7) Нетто эффект резервов на ОПУ | B56: Восстановление резервов | C56: =Data_BI!#REF! -> #REF! | D56: Прочее | E56: RUB | F56: ‭РВП по 611-П Восстановление резерва по вложениям в долговые ЦБ прочих резидентов оцениваемых по СС через ПСД ‬ | G56: 2923652.4 | H56: 45658 | I56: Согласно ст 292 НК РФ бан имеет право признавать только Резерв поод ссудную задолженность по 590-П | J56: Учетные данные | K56: Резервы | L56: =(ISNUMBER(G56))-1 -> 0
A57: 3) FX | B57: Безнал | C57: Доход безнал | D57: Прочее | E57: EUR | G57: 2776328.1 | H57: 45658 | J57: Учетные данные | K57: Доход | L57: =(ISNUMBER(G57))-1 -> 0
A58: 2) Комиссии - нетто | B58: Комиссионный доход | C58: РКО ЮЛ | D58: ЮЛ | E58: RUB | F58: ‭Комиссия за доп. услуги ЮР. ЛИЦ (без НДС) в ин.валюте‬ | G58: 2603349 | H58: 45658 | J58: Учетные данные | K58: Доход | L58: =(ISNUMBER(G58))-1 -> 0
A59: 2) Комиссии - нетто | B59: Комиссионный доход | C59: Пакеты обслуживания | D59: Прочее | E59: RUB | F59: ‭Комиссия за пакет обсуживания "ПРЕМИАЛЬНЫЙ" в руб.‬ | G59: 2556377 | H59: 45658 | J59: Учетные данные | K59: Доход | L59: =(ISNUMBER(G59))-1 -> 0
A60: 4) ЧТД | B60: Доходы от операций с ЦБ | C60: Доходы от операций с ЦБ | D60: Прочее | E60: RUB | F60: ‭Доходы от увеличения амортизированной стоимости облигаций прочих резидентов‬ | G60: 2533455.6 | H60: 45658 | J60: Учетные данные | K60: Доход | L60: =(ISNUMBER(G60))-1 -> 0
A61: 3) FX | B61: Безнал | C61: Доход безнал | D61: Прочее | E61: CNY | G61: 2398957 | H61: 45658 | J61: Учетные данные | K61: Доход | L61: =(ISNUMBER(G61))-1 -> 0
A62: 2) Комиссии - нетто | B62: Комиссионный доход | C62: Индивидуальные предприниматели | D62: Прочее | E62: RUB | F62: ‭Комиссия за перевод средств ИП, в руб. без НДС‬ | G62: 2330907.9 | H62: 45658 | J62: Учетные данные | K62: Доход | L62: =(ISNUMBER(G62))-1 -> 0
A63: 1) ЧПД | B63: Процентный доход | C63: Проценты по кредитам ЮЛ/МБК | D63: Прочее | E63: RUB | F63: ‭Процентные доходы по межбанковским кредитам международным финансовым организациям в рублях‬ | G63: 2278356.1 | H63: 45658 | J63: Учетные данные | K63: Доход | L63: =(ISNUMBER(G63))-1 -> 0
A64: 3) FX | B64: Безнал | C64: Доход безнал | D64: Прочее | E64: TRY | G64: 2256652 | H64: 45658 | J64: Учетные данные | K64: Доход | L64: =(ISNUMBER(G64))-1 -> 0
A65: 1) ЧПД | B65: Процентный доход | C65: Проценты по ЦБ в портфеле | D65: Прочее | E65: RUB | F65: ‭НКД по облигациям РФ по АС в валюте‬ | G65: 1840329.3 | H65: 45658 | J65: Учетные данные | K65: Доход | L65: =(ISNUMBER(G65))-1 -> 0
A66: 2) Комиссии - нетто | B66: Комиссионный доход | C66: Пакеты обслуживания | D66: Прочее | E66: RUB | F66: ‭Комиссия за пакет обсуживания "ИНДИВИДУАЛЬНЫЙ" в руб.‬ | G66: 1765000 | H66: 45658 | J66: Учетные данные | K66: Доход | L66: =(ISNUMBER(G66))-1 -> 0
A67: 7) Нетто эффект резервов на ОПУ | B67: Восстановление резервов | C67: =Data_BI!$B9 -> Безнал | D67: ФЛ | E67: RUB | F67: ‭РВП по 611-п Доходы от восст.резервов по % кредит.физическим лицам ‬ | G67: 1727275.1 | H67: 45658 | I67: Согласно ст 292 НК РФ бан имеет право признавать только Резерв поод ссудную задолженность по 590-П | J67: Учетные данные | K67: Резервы | L67: =(ISNUMBER(G67))-1 -> 0
A68: 2) Комиссии - нетто | B68: Комиссионный доход | C68: РКО ФЛ | D68: ФЛ | E68: RUB | F68: ‭Комиссия за расчетное обслуживание ФИЗ. ЛИЦ в рублях‬ | G68: 1684148.8 | H68: 45658 | J68: Учетные данные | K68: Доход | L68: =(ISNUMBER(G68))-1 -> 0
A69: 2) Комиссии - нетто | B69: Комиссионный доход | C69: Пакеты обслуживания | D69: Прочее | E69: RUB | F69: ‭Комиссия за пакет обслуживания "PRIVATE BANKING" в руб.‬ | G69: 1653000 | H69: 45658 | J69: Учетные данные | K69: Доход | L69: =(ISNUMBER(G69))-1 -> 0
A70: 1) ЧПД | B70: Процентный доход | C70: Проценты по ЦБ в портфеле | D70: Прочее | E70: RUB | F70: ‭НКД по облигациям прочих нерезидентов по АС в рублях‬ | G70: 1551520.2 | H70: 45658 | J70: Учетные данные | K70: Доход | L70: =(ISNUMBER(G70))-1 -> 0
A71: 2) Комиссии - нетто | B71: Комиссионный доход | C71: РКО ФЛ | D71: ФЛ | E71: RUB | F71: ‭Комиссия за кассовое обслуживание ФИЗИЧ.ЛИЦ в рублях‬ | G71: 1476259.9 | H71: 45658 | J71: Учетные данные | K71: Доход | L71: =(ISNUMBER(G71))-1 -> 0
A72: 3) FX | B72: Безнал | C72: Доход безнал | D72: Прочее | E72: AED | G72: 1399532.5 | H72: 45658 | J72: Учетные данные | K72: Доход | L72: =(ISNUMBER(G72))-1 -> 0
A73: 7) Нетто эффект резервов на ОПУ | B73: Восстановление резервов | C73: =Data_BI!#REF! -> #REF! | D73: ЮЛ | E73: RUB | F73: ‭РВПС по 590-П Доходы от восст.резервов по предоставл.кредитам юр.лицам‬ | G73: 1319165.3 | H73: 45658 | J73: Учетные данные | K73: Резервы | L73: =(ISNUMBER(G73))-1 -> 0
A74: 4) ЧТД | B74: Доходы от операций с ЦБ | C74: Доходы от операций с ЦБ | D74: Прочее | E74: RUB | F74: ‭Доходы от увелич.стоим. облиг-й Российской Федерации (504)‬ | G74: 1250385.8 | H74: 45658 | J74: Учетные данные | K74: Доход | L74: =(ISNUMBER(G74))-1 -> 0
A75: 2) Комиссии - нетто | B75: Комиссионный доход | C75: РКО ФЛ | D75: ФЛ | E75: RUB | F75: ‭Комиссия за перевод средств по СБП со счетов ФИЗ.ЛИЦ в руб.‬ | G75: 1227355.2 | H75: 45658 | J75: Учетные данные | K75: Доход | L75: =(ISNUMBER(G75))-1 -> 0
A76: 2) Комиссии - нетто | B76: Комиссионный доход | C76: РКО ФЛ | D76: Прочее | E76: RUB | F76: ‭Комиссия за переводы с карты Цифра банка на карты других банков в руб.‬ | G76: 1201011.6 | H76: 45658 | J76: Учетные данные | K76: Доход | L76: =(ISNUMBER(G76))-1 -> 0
A77: 3) FX | B77: Безнал | C77: Доход безнал | D77: Прочее | E77: CNY | G77: 1164780 | H77: 45658 | J77: Учетные данные | K77: Доход | L77: =(ISNUMBER(G77))-1 -> 0
A78: 3) FX | B78: Наличные | C78: Доход налич | D78: Прочее | E78: CNY | G78: 1145171 | H78: 45658 | J78: Учетные данные | K78: Доход | L78: =(ISNUMBER(G78))-1 -> 0
A79: 7) Нетто эффект резервов на ОПУ | B79: Восстановление резервов | C79: =Data_BI!#REF! -> #REF! | D79: Прочее | E79: RUB | F79: ‭Доходы от восстановления оценочных резервов по облигациям прочих резидентов‬ | G79: 1133637.7 | H79: 45658 | J79: Учетные данные | K79: Резервы | L79: =(ISNUMBER(G79))-1 -> 0
A80: 2) Комиссии - нетто | B80: Комиссионный доход | C80: РКО ФЛ | D80: ФЛ | E80: RUB | F80: ‭Комиссия за переводы ФИЗ.ЛИЦ (Bro.acc.) в рублях ‬ | G80: 1084712.5 | H80: 45658 | J80: Учетные данные | K80: Доход | L80: =(ISNUMBER(G80))-1 -> 0
A81: 2) Комиссии - нетто | B81: Комиссионный доход | C81: Индивидуальные предприниматели | D81: Прочее | E81: RUB | F81: ‭Комиссия за пакет обслуживания ИНДИВИД. ПРЕДПР. ‬ | G81: 1050020 | H81: 45658 | J81: Учетные данные | K81: Доход | L81: =(ISNUMBER(G81))-1 -> 0
A82: 7) Нетто эффект резервов на ОПУ | B82: Восстановление резервов | C82: =Data_BI!#REF! -> #REF! | D82: ФЛ | E82: RUB | F82: ‭Доходы от восстановления оценочных резервов по кредитам физических лиц резидентов‬ | G82: 1042904 | H82: 45658 | J82: Учетные данные | K82: Резервы | L82: =(ISNUMBER(G82))-1 -> 0
A83: 2) Комиссии - нетто | B83: Комиссионный доход | C83: РКО ФЛ | D83: Прочее | E83: RUB | F83: ‭Комиссия за переводы с карты Цифра банка на карты других банков в иностранной валюте‬ | G83: 1015773 | H83: 45658 | J83: Учетные данные | K83: Доход | L83: =(ISNUMBER(G83))-1 -> 0
A84: 1) ЧПД | B84: Процентный доход | C84: Доход от амортизации корректировок по ссудам | D84: Прочее | E84: RUB | F84: ‭Доходы от амортизации корректировок по ссудам ф/л резидентов‬ | G84: 1014548.4 | H84: 45658 | J84: Учетные данные | K84: Доход | L84: =(ISNUMBER(G84))-1 -> 0
A85: 2) Комиссии - нетто | B85: Комиссионный доход | C85: РКО ЮЛ | D85: ЮЛ | E85: RUB | F85: ‭Комиссия за расчетное обслуживание ЮРИД.ЛИЦ в рублях‬ | G85: 1008193 | H85: 45658 | J85: Учетные данные | K85: Доход | L85: =(ISNUMBER(G85))-1 -> 0
A86: 3) FX | B86: Безнал | C86: Доход безнал | D86: Прочее | E86: TRY | G86: 827866.49 | H86: 45658 | J86: Учетные данные | K86: Доход | L86: =(ISNUMBER(G86))-1 -> 0
A87: 2) Комиссии - нетто | B87: Комиссионный доход | C87: Платежные системы | D87: Прочее | E87: RUB | F87: ‭Расчеты с МПС Visa в руб‬ | G87: 801279.52 | H87: 45658 | J87: Учетные данные | K87: Доход | L87: =(ISNUMBER(G87))-1 -> 0
A88: 2) Комиссии - нетто | B88: Комиссионный доход | C88: РКО ФЛ | D88: ФЛ | E88: RUB | F88: ‭Комиссия за перевод средств со счетов физ.лиц принятых по сист. ДБО в рублях‬ | G88: 739630.36 | H88: 45658 | J88: Учетные данные | K88: Доход | L88: =(ISNUMBER(G88))-1 -> 0
A89: 7) Нетто эффект резервов на ОПУ | B89: Восстановление резервов | C89: =Data_BI!#REF! -> #REF! | D89: ЮЛ | E89: RUB | F89: ‭Доходы от создания оценочных резервов по кредитам юр. лиц резидентов (негос. фин. орг-циям)‬ | G89: 708878.63 | H89: 45658 | J89: Учетные данные | K89: Резервы | L89: =(ISNUMBER(G89))-1 -> 0
A90: 3) FX | B90: Наличные | C90: Доход налич | D90: Прочее | E90: AED | G90: 706237.33 | H90: 45658 | J90: Учетные данные | K90: Доход | L90: =(ISNUMBER(G90))-1 -> 0
A91: 7) Нетто эффект резервов на ОПУ | B91: Восстановление резервов | C91: =Data_BI!#REF! -> #REF! | D91: Прочее | E91: RUB | F91: ‭РВП по 611-п Доходы от восст.резервов по процентам по МБК‬ | G91: 697782.22 | H91: 45658 | J91: Учетные данные | K91: Резервы | L91: =(ISNUMBER(G91))-1 -> 0
A92: 2) Комиссии - нетто | B92: Комиссионный доход | C92: Пакеты обслуживания | D92: Прочее | E92: RUB | F92: ‭Комиссия за пакет обсуживания "ПРЕМИАЛЬНЫЙ" в руб.‬ | G92: 668161.56 | H92: 45658 | J92: Учетные данные | K92: Доход | L92: =(ISNUMBER(G92))-1 -> 0
A93: 4) ЧТД | B93: Доходы от операций с ЦБ | C93: Доходы от операций с ЦБ | D93: Прочее | E93: RUB | F93: ‭Доходы от увеличения амортизированной стоимости облигаций кредитных организаций‬ | G93: 665239.44 | H93: 45658 | J93: Учетные данные | K93: Доход | L93: =(ISNUMBER(G93))-1 -> 0
A94: 2) Комиссии - нетто | B94: Комиссионный доход | C94: РКО ФЛ | D94: Прочее | E94: RUB | F94: ‭Переводы с карты ООО «Цифра банк» на карты/счета других банков, на карты ООО «Цифра банк» с использованием механизма Р2Р в рублях.‬ | G94: 652479.74 | H94: 45658 | J94: Учетные данные | K94: Доход | L94: =(ISNUMBER(G94))-1 -> 0
A95: 2) Комиссии - нетто | B95: Комиссионный доход | C95: РКО ФЛ | D95: Прочее | E95: RUB | F95: ‭Комиссия за внешние переводы с карточных счетов на счета в другие кредитные организации в руб.‬ | G95: 649519.78 | H95: 45658 | J95: Учетные данные | K95: Доход | L95: =(ISNUMBER(G95))-1 -> 0
A96: 2) Комиссии - нетто | B96: Комиссионный доход | C96: Пакеты обслуживания | D96: Прочее | E96: RUB | F96: ‭Комиссия за пакет обсуживания "ИНДИВИДУАЛЬНЫЙ" в руб.‬ | G96: 625000.64 | H96: 45658 | J96: Учетные данные | K96: Доход | L96: =(ISNUMBER(G96))-1 -> 0
A97: 3) FX | B97: Безнал | C97: Доход безнал | D97: Прочее | E97: AED | G97: 615142.24 | H97: 45658 | J97: Учетные данные | K97: Доход | L97: =(ISNUMBER(G97))-1 -> 0
A98: 2) Комиссии - нетто | B98: Комиссионный доход | C98: Индивидуальные предприниматели | D98: Прочее | E98: RUB | F98: ‭Комиссия за перевод средств ИП, в ин.вал. без НДС‬ | G98: 575544 | H98: 45658 | J98: Учетные данные | K98: Доход | L98: =(ISNUMBER(G98))-1 -> 0
A99: 2) Комиссии - нетто | B99: Комиссионный доход | C99: РКО ЮЛ | D99: ЮЛ | E99: RUB | F99: ‭Комиссия за пакет услуг ЮР. ЛИЦ (Авансовая)‬ | G99: 552300 | H99: 45658 | J99: Учетные данные | K99: Доход | L99: =(ISNUMBER(G99))-1 -> 0
A100: 1) ЧПД | B100: Процентный доход | C100: Проценты по кредитам ЮЛ/МБК | D100: ЮЛ | E100: RUB | F100: ‭Процентам по кредитам предоставл. юр.лицам-нерезидентам‬ | G100: 552054.79 | H100: 45658 | J100: Учетные данные | K100: Доход | L100: =(ISNUMBER(G100))-1 -> 0
...

Sheet Лист4
A1: Тип проверки | B1: Наименование поля | C1: Пример данных | D1: Примечания
A2: Проверка по справочнику | B2: Название | C2: 1) ЧПД
A3: Проверка по справочнику | B3: Тип | C3: Процентный доход
A4: Проверка по справочнику | B4: 2уровень | C4: % по корсчетам в банках-нерезидентах
A5: Проверка по справочнику | B5: Ф/Ю | C5: ФЛ, ЮЛ, ИП | D5: Актуализировать данные
A6: Без проверки | B6: Расшифровка | C6: # | D6: Актуализировать данные
A7: Не нужно | B7: Название счета | C7: ‭% по корсчетам в банках- нерезидентах в иностранных валютах‬ | D7: Кажется тут лежат данные из расшифровки
A8: Проверка тип данных и заполненность | B8: Сумма | C8: 99411.47 | D8: Проверить пустые значения ( почти 1000 строк)
A9: Не нужно | B9: Сумма_модуль | C9: =IFERROR(IMABS([1]Data_BI!C$7),0) -> 0
A10: Проверка тип данных и заполненность | B10: Месяц | C10: Январь | D10: Отдавать в формате YYYY-MM-DD
A11: Не нужно | B11: Счет | C11: 7.060181e+19
A12: Не нужно | B12: Наименование клиента | C12: ‭Общество с ограниченной ответственностью "Цифра банк"‬
A13: Не нужно | B13: Код страны | C13: RU
A14: Без проверки | B14: Комментарии | C14: - | D14: Обединить с еще одним полем Комментарии, отдавать все в одном
A15: Проверка по справочнику | B15: УК | C15: Учетные данные
A16: Проверка по справочнику | B16: Группа | C16: Доход/Расход/Резервы | D16: Резервы
A17: Объединить с Комметарии | B17: Комментарии | C17: - | D17: Обединить с еще одним полем Комментарии, отдавать все в одном
A18: Добавить поле | B18: Код валюты | C18: RUB/USD/KZT … | D18: Мне кажется, он уже где-то есть. Просто нужно перенести в правильный столбец. А то он то ли в расшифровке лежит, код валюты, то ли еще где-то. То ли в наименовании счета.
A19: Добавить поле | B19: Страна резидентства (или хотя бы рез/нерез) | C19: RU/KZ/AM/KG | Резидент/Нерезидент | D19: Если нет возможности отдавать страну резидентство, достаточно просто резидент, не резидент.
A20: Добавить поле | B20: Тип деятельности | C20: Операционная/Инвестиционная/Переоценка | D20: Если есть такая возможность
A21: Добавить поле | B21: EBITDA | C21: true/false | D21: Отметить поля, которые входят в расчет ебитды, можно, наверное, без него, если согласовать четкий список параметров по которым я сам мог бы посчитать ебитду
